repmsa.py
repmsa-0.1.6.dist-info/METADATA
repmsa-0.1.6.dist-info/WHEEL
repmsa-0.1.6.dist-info/top_level.txt
repmsa-0.1.6.dist-info/RECORD
